Metadata-Version: 2.1
Name: forest-puller
Version: 1.4.1
Summary: A package for retrieving data concerning forests on the European continent.
Home-page: http://github.com/xapple/forest_puller/
Author: Lucas Sinclair
Author-email: lucas.sinclair@me.com
License: MIT
Platform: UNKNOWN
